vcomp/__init__.py
vcomp/compress.py
vcomp/main.py
vcomp-1.1.0.dist-info/LICENSE
vcomp-1.1.0.dist-info/METADATA
vcomp-1.1.0.dist-info/WHEEL
vcomp-1.1.0.dist-info/entry_points.txt
vcomp-1.1.0.dist-info/top_level.txt
vcomp-1.1.0.dist-info/RECORD
